main.py
eap_mcp_server-0.1.2.dist-info/METADATA
eap_mcp_server-0.1.2.dist-info/WHEEL
eap_mcp_server-0.1.2.dist-info/entry_points.txt
eap_mcp_server-0.1.2.dist-info/top_level.txt
eap_mcp_server-0.1.2.dist-info/RECORD
