Metadata-Version: 2.4
Name: eap-mcp-server
Version: 0.1.2
Summary: EAP MCP Server
Requires-Python: >=3.12
Requires-Dist: argparse>=1.4.0
Requires-Dist: matplotlib>=3.10.3
Requires-Dist: mcp>=1.6.0
Requires-Dist: pandas>=2.2.3
Requires-Dist: requests>=2.32.3
